{
    "DATA":[
        {"CHARACTER":"Joel_think"},
        {"TEXT":"A royal letter...? On Pudding Day?"},
        {"TEXT":"Did this come from your pa, kid?"},
        {"CHARACTER":"Hugo_sad"},
        {"TEXT":"Um, I don't know... it was just in the station! Am I in trouble? O-Or, um... is dad in trouble?", "TIME":0.03},
        {"CHARACTER":"Joel_think"},
        {"TEXT":"No, it's just... for an enemy general to announce a visit on Pudding Day..."},
        {"CHARACTER":"Hugo_serious"},
        {"TEXT":"W-Wait, did you say 'enemy general'?", "TIME":0.03},
        {"CHARACTER":"Protagonist"},
        {"TEXT":"..!", "TIME":0.01},
        {"CHARACTER":"Joel_smile"},
        {"TEXT":"Heh, slipped that one out. You're a smart kid, kid."},
        {"CHARACTER":"Joel_think"},
        {"TEXT":"Yeah, I did say that, but... if your dad sent us a letter today, it can only mean... he's announcing peace."},
        {"CHARACTER":"Hugo_huh"},
        {"TEXT":"Oh... peace?", "TIME":0.03},
        {"CHARACTER":"Joel_think"},
        {"TEXT":"Which I find weird, if I'm being completely honest."},
        {"CHARACTER":"Joel_sad"},
        {"TEXT":"Did your dad tell you this? His troops just demolished us in the last battle. I was expecting an advance, but..."},
        {"CHARACTER":"Joel_smile"},
        {"TEXT":"Heh, maybe your pa is a good person after all, eh, kid?"},
        {"CHARACTER":"Hugo_huh"},
        {"TEXT":"I... hmm.", "TIME":0.03},
        {"CHARACTER":"Joel_smile"},
        {"TEXT":"I'll personally greet him when he touches down here. Thank you for this, mailman... a soldier can finally rest easy today."},
        {"CHARACTER":"Narrator"},
        {"TEXT":"With this, the soldier returns to his hideout, and you two go back to your rocket-box.", "NARRATOR":true},
        {"END":"END"}
    ]
}